eptium/__init__.py
eptium/_version.py
eptium/example.py
eptium/template_state.json
eptium/widget.py
eptium/tests/__init__.py
eptium/tests/conftest.py
eptium/tests/test_example.py
eptium/tests/test_nbextension_path.py
eptium-0.2.0.dist-info/METADATA
eptium-0.2.0.dist-info/WHEEL
eptium-0.2.0.dist-info/licenses/LICENSE
eptium-0.2.0.dist-info/RECORD
