Metadata-Version: 2.4
Name: eptium
Version: 0.2.0
Summary: A jupyter widget to display COPC and COGS data from Eptium.
Project-URL: Homepage, https://github.com/hobuinc/eptium-python
Author-email: Ognyan Moore <ogi@hobu.co>
License:                                  Apache License
License-File: LICENSE
Keywords: IPython,Jupyter,Widgets
Classifier: Framework :: Jupyter
Classifier: Intended Audience :: Developers
Classifier: Intended Audience :: Science/Research
Classifier: License :: OSI Approved :: BSD License
Classifier: Programming Language :: Python
Classifier: Programming Language :: Python :: 3
Classifier: Programming Language :: Python :: 3.9
Classifier: Programming Language :: Python :: 3.10
Classifier: Programming Language :: Python :: 3.11
Classifier: Programming Language :: Python :: 3.12
Requires-Python: >=3.9
Requires-Dist: ipython
Requires-Dist: ipywidgets>=7.0.0
Requires-Dist: jupyter-core
Provides-Extra: docs
Requires-Dist: jupyter-sphinx; extra == 'docs'
Requires-Dist: nbsphinx; extra == 'docs'
Requires-Dist: nbsphinx-link; extra == 'docs'
Requires-Dist: pypandoc; extra == 'docs'
Requires-Dist: pytest-check-links; extra == 'docs'
Requires-Dist: recommonmark; extra == 'docs'
Requires-Dist: sphinx-rtd-theme; extra == 'docs'
Requires-Dist: sphinx>=1.5; extra == 'docs'
Provides-Extra: examples
Provides-Extra: test
Requires-Dist: nbval; extra == 'test'
Requires-Dist: pytest>=6.0; extra == 'test'
